Metadata-Version: 2.1
Name: scikit-optimize
Version: 0.10.2
Summary: Sequential model-based optimization toolbox.
Author: The scikit-optimize contributors
License: BSD 3-clause
Project-URL: Homepage, https://scikit-optimize.readthedocs.io/en/latest/contents.html
Project-URL: Source Code, https://github.com/holgern/scikit-optimize
Project-URL: Bug Tracker, https://github.com/holgern/scikit-optimize/issues
Classifier: Intended Audience :: Science/Research
Classifier: Intended Audience :: Developers
Classifier: License :: OSI Approved :: BSD License
Classifier: Programming Language :: Python
Classifier: Topic :: Software Development
Classifier: Topic :: Scientific/Engineering
Classifier: Operating System :: Microsoft :: Windows
Classifier: Operating System :: POSIX
Classifier: Operating System :: Unix
Classifier: Operating System :: MacOS
Classifier: Programming Language :: Python :: 3.8
Classifier: Programming Language :: Python :: 3.9
Classifier: Programming Language :: Python :: 3.10
Classifier: Programming Language :: Python :: 3.11
Classifier: Programming Language :: Python :: 3.12
License-File: LICENSE
License-File: AUTHORS.md
Requires-Dist: joblib>=0.11
Requires-Dist: pyaml>=16.9
Requires-Dist: numpy>=1.20.3
Requires-Dist: scipy>=1.1.0
Requires-Dist: scikit-learn>=1.0.0
Requires-Dist: packaging>=21.3
Provides-Extra: plots
Requires-Dist: matplotlib>=2.0.0; extra == "plots"
Provides-Extra: dev
Requires-Dist: flake8; extra == "dev"
Requires-Dist: pandas; extra == "dev"
Requires-Dist: pytest; extra == "dev"
Requires-Dist: pytest-cov; extra == "dev"
Requires-Dist: pytest-xdist; extra == "dev"
Provides-Extra: doc
Requires-Dist: memory_profiler; extra == "doc"
Requires-Dist: numpydoc; extra == "doc"
Requires-Dist: sphinx; extra == "doc"
Requires-Dist: pydata-sphinx-theme; extra == "doc"
Requires-Dist: sphinx-gallery>=0.6; extra == "doc"
